{
  "data": [
    {
      "messageId": "b5f8015f-900b-4034-b124-ea7126c93c75-1712267696044",
      "messageSentAt": "04/04/2024 21:54:56",
      "messageExecutionStartedAt": "04/04/2024 21:54:56",
      "messageExecutedAt": "05/04/2024 21:54:57",
      "createdAt": "03/04/2024 21:54:57",
      "updatedAt": "04/04/2024 21:55:26"
    },
    {
      "messageId": "0272ffb4-c8b2-4e58-9c08-e3c42459d4b9-1712267696036",
      "messageSentAt": "04/04/2024 21:54:56",
      "messageExecutionStartedAt": "04/04/2024 21:54:56",
      "messageExecutedAt": "06/04/2024 21:54:57",
      "createdAt": "04/04/2024 21:54:56",
      "updatedAt": "04/04/2024 21:55:26"
    },
    {
      "messageId": "10684544-0b26-449a-8731-164e027fd7e0-1712267696032",
      "messageSentAt": "04/04/2024 21:54:56",
      "messageExecutionStartedAt": "04/04/2024 21:54:56",
      "messageExecutedAt": "04/04/2024 21:54:56",
      "createdAt": "04/04/2024 21:54:56",
      "updatedAt": "04/04/2024 21:55:26"
    },
    {
      "messageId": "d8519df3-bcc6-47bc-8dd7-663e485b9b70-1712267696024",
      "messageSentAt": "04/04/2024 21:54:56",
      "messageExecutionStartedAt": "04/04/2024 21:54:56",
      "messageExecutedAt": "04/04/2024 21:54:56",
      "createdAt": "04/04/2024 21:54:56",
      "updatedAt": "04/04/2024 21:55:26"
    },
    {
      "messageId": "06748e08-4f67-4f9c-b181-a163e987c95b-1712267696021",
      "messageSentAt": "04/04/2024 21:54:56",
      "messageExecutionStartedAt": "04/04/2024 21:54:56",
      "messageExecutedAt": "04/04/2024 21:54:56",
      "createdAt": "04/04/2024 21:54:56",
      "updatedAt": "04/04/2024 21:55:25"
    },
    {
      "messageId": "81d11eaf-746f-4ccf-b23b-beda64ab8cbe-1712267095832",
      "messageSentAt": "04/04/2024 21:44:55",
      "messageExecutionStartedAt": "04/04/2024 21:44:56",
      "messageExecutedAt": "04/04/2024 21:44:57",
      "createdAt": "04/04/2024 21:44:55",
      "updatedAt": "04/04/2024 21:45:25"
    },
    {
      "messageId": "1bae35c8-9b40-4818-91e1-88f651656744-1712267095827",
      "messageSentAt": "04/04/2024 21:44:55",
      "messageExecutionStartedAt": "04/04/2024 21:44:56",
      "messageExecutedAt": "04/04/2024 21:44:56",
      "createdAt": "04/04/2024 21:44:55",
      "updatedAt": "04/04/2024 21:45:25"
    },
    {
      "messageId": "85549c10-5a0b-4a63-aef7-7d418f6d1b6a-1712267095822",
      "messageSentAt": "04/04/2024 21:44:55",
      "messageExecutionStartedAt": "04/04/2024 21:44:56",
      "messageExecutedAt": "04/04/2024 21:44:56",
      "createdAt": "04/04/2024 21:44:55",
      "updatedAt": "04/04/2024 21:45:25"
    },
    {
      "messageId": "7a3476a5-9b57-46b4-9b0b-d20f7f5c3686-1712267095815",
      "messageSentAt": "04/04/2024 21:44:55",
      "messageExecutionStartedAt": "04/04/2024 21:44:55",
      "messageExecutedAt": "04/04/2024 21:44:56",
      "createdAt": "04/04/2024 21:44:55",
      "updatedAt": "04/04/2024 21:45:25"
    },
    {
      "messageId": "ec216c1c-0dbe-4ef9-8a81-f0ad21f0f6cc-1712267095809",
      "messageSentAt": "04/04/2024 21:44:55",
      "messageExecutionStartedAt": "04/04/2024 21:44:55",
      "messageExecutedAt": "04/04/2024 21:44:56",
      "createdAt": "04/04/2024 21:44:55",
      "updatedAt": "04/04/2024 21:45:25"
    },
    {
      "messageId": "eb8f6517-9f65-44cf-adc5-08ab65a83835-1712266495417",
      "messageSentAt": "04/04/2024 21:34:55",
      "messageExecutionStartedAt": "04/04/2024 21:34:56",
      "messageExecutedAt": "04/04/2024 21:34:56",
      "createdAt": "04/04/2024 21:34:55",
      "updatedAt": "04/04/2024 21:35:25"
    },
    {
      "messageId": "37c7f130-423e-4d56-9901-acf96479ad11-1712266495405",
      "messageSentAt": "04/04/2024 21:34:55",
      "messageExecutionStartedAt": "04/04/2024 21:34:55",
      "messageExecutedAt": "04/04/2024 21:34:56",
      "createdAt": "04/04/2024 21:34:55",
      "updatedAt": "04/04/2024 21:35:25"
    },
    {
      "messageId": "abc2154c-65cf-4970-b144-4a2d2653ffa8-1712266495400",
      "messageSentAt": "04/04/2024 21:34:55",
      "messageExecutionStartedAt": "04/04/2024 21:34:55",
      "messageExecutedAt": "04/04/2024 21:34:55",
      "createdAt": "04/04/2024 21:34:55",
      "updatedAt": "04/04/2024 21:35:25"
    },
    {
      "messageId": "2a8304bc-b044-4d5a-b863-e3765dbcf15a-1712266495396",
      "messageSentAt": "04/04/2024 21:34:55",
      "messageExecutionStartedAt": "04/04/2024 21:34:55",
      "messageExecutedAt": "04/04/2024 21:34:55",
      "createdAt": "04/04/2024 21:34:55",
      "updatedAt": "04/04/2024 21:35:25"
    },
    {
      "messageId": "4392c30e-3092-48cd-8e11-af312ecb2493-1712266495388",
      "messageSentAt": "04/04/2024 21:34:55",
      "messageExecutionStartedAt": "04/04/2024 21:34:55",
      "messageExecutedAt": "04/04/2024 21:34:56",
      "createdAt": "04/04/2024 21:34:55",
      "updatedAt": "04/04/2024 21:35:25"
    },
    {
      "messageId": "7ed3fa52-cbb9-405d-8e55-a3d4a3aad7ff-1712265894886",
      "messageSentAt": "04/04/2024 21:24:54",
      "messageExecutionStartedAt": "04/04/2024 21:24:56",
      "messageExecutedAt": "04/04/2024 21:24:56",
      "createdAt": "04/04/2024 21:24:54",
      "updatedAt": "04/04/2024 21:25:24"
    },
    {
      "messageId": "8291a763-804d-4a95-a952-e58bebb3d292-1712265894869",
      "messageSentAt": "04/04/2024 21:24:54",
      "messageExecutionStartedAt": "04/04/2024 21:24:56",
      "messageExecutedAt": "04/04/2024 21:24:56",
      "createdAt": "04/04/2024 21:24:54",
      "updatedAt": "04/04/2024 21:25:24"
    },
    {
      "messageId": "219f3a57-1afc-4256-9044-c9f51189b701-1712265894861",
      "messageSentAt": "04/04/2024 21:24:54",
      "messageExecutionStartedAt": "04/04/2024 21:24:55",
      "messageExecutedAt": "04/04/2024 21:24:56",
      "createdAt": "04/04/2024 21:24:54",
      "updatedAt": "04/04/2024 21:25:24"
    },
    {
      "messageId": "d5e270ed-b682-488d-872c-e305fce4fe25-1712265894853",
      "messageSentAt": "04/04/2024 21:24:54",
      "messageExecutionStartedAt": "04/04/2024 21:24:54",
      "messageExecutedAt": "04/04/2024 21:24:55",
      "createdAt": "04/04/2024 21:24:54",
      "updatedAt": "04/04/2024 21:25:24"
    },
    {
      "messageId": "c2b59247-a5be-4ec3-8822-87dd33508834-1712265894825",
      "messageSentAt": "04/04/2024 21:24:54",
      "messageExecutionStartedAt": "04/04/2024 21:24:54",
      "messageExecutedAt": "04/04/2024 21:24:55",
      "createdAt": "04/04/2024 21:24:54",
      "updatedAt": "04/04/2024 21:25:24"
    }
  ]
}
